README.md
setup.py
dj_scheduledtasks.egg-info/PKG-INFO
dj_scheduledtasks.egg-info/SOURCES.txt
dj_scheduledtasks.egg-info/dependency_links.txt
dj_scheduledtasks.egg-info/top_level.txt
scheduledtasks/__init__.py
scheduledtasks/admin.py
scheduledtasks/apps.py
scheduledtasks/models.py
scheduledtasks/runner.py
scheduledtasks/tests.py
scheduledtasks/views.py
scheduledtasks/management/commands/__init__.py
scheduledtasks/management/commands/run_schedule.py
scheduledtasks/migrations/0001_initial.py
scheduledtasks/migrations/0002_auto_20191216_1031.py
scheduledtasks/migrations/0003_auto_20191216_1036.py
scheduledtasks/migrations/__init__.py