Metadata-Version: 2.1
Name: dj-scheduledtasks
Version: 0.0.3
Summary: ...
Home-page: https://gitlab.com/.../...
Author: AppointmentGuru
Author-email: tech@appointmentguru.co
License: UNKNOWN
Platform: UNKNOWN
Classifier: Programming Language :: Python :: 3
Classifier: Operating System :: OS Independent
